Workbook

Sheet Daily_Entry
A1: Date | B1: Loads | C1: Total Income | D1: GPay Amount | E1: Cash Amount | F1: Diesel Cost | G1: Other Expenses | H1: Remarks | I1: Total Expenses | J1: Profit
I2: =F2+G2 | J2: =C2-I2
I3: =F3+G3 | J3: =C3-I3
I4: =F4+G4 | J4: =C4-I4
I5: =F5+G5 | J5: =C5-I5
I6: =F6+G6 | J6: =C6-I6
I7: =F7+G7 | J7: =C7-I7
I8: =F8+G8 | J8: =C8-I8
I9: =F9+G9 | J9: =C9-I9
I10: =F10+G10 | J10: =C10-I10
I11: =F11+G11 | J11: =C11-I11
I12: =F12+G12 | J12: =C12-I12
I13: =F13+G13 | J13: =C13-I13
... I999: =F999+G999 | J999: =C999-I999

Sheet Driver_Salary
A1: Month | B1: Salary Amount | C1: Paid Date | D1: Mode | E1: Remarks

Sheet Jan
A1: Metric | B1: Value
A2: Total Loads | B2: =SUMPRODUCT((MONTH(Daily_Entry!A2:A999)=1)*(Daily_Entry!B2:B999))
A3: Total Income | B3: =SUMPRODUCT((MONTH(Daily_Entry!A2:A999)=1)*(Daily_Entry!C2:C999))
A4: Total GPay | B4: =SUMPRODUCT((MONTH(Daily_Entry!A2:A999)=1)*(Daily_Entry!D2:D999))
A5: Total Cash | B5: =SUMPRODUCT((MONTH(Daily_Entry!A2:A999)=1)*(Daily_Entry!E2:E999))
A6: Diesel Expense | B6: =SUMPRODUCT((MONTH(Daily_Entry!A2:A999)=1)*(Daily_Entry!F2:F999))
A7: Other Expenses | B7: =SUMPRODUCT((MONTH(Daily_Entry!A2:A999)=1)*(Daily_Entry!G2:G999))
A8: Driver Salary | B8: =SUMIF(Driver_Salary!A:A,"Jan",Driver_Salary!B:B)
A9: Total Expenses | B9: =B6+B7+B8
A10: Net Profit | B10: =B3-B9

Sheet Feb
A1: Metric | B1: Value
A2: Total Loads | B2: =SUMPRODUCT((MONTH(Daily_Entry!A2:A999)=2)*(Daily_Entry!B2:B999))
A3: Total Income | B3: =SUMPRODUCT((MONTH(Daily_Entry!A2:A999)=2)*(Daily_Entry!C2:C999))
A4: Total GPay | B4: =SUMPRODUCT((MONTH(Daily_Entry!A2:A999)=2)*(Daily_Entry!D2:D999))
A5: Total Cash | B5: =SUMPRODUCT((MONTH(Daily_Entry!A2:A999)=2)*(Daily_Entry!E2:E999))
A6: Diesel Expense | B6: =SUMPRODUCT((MONTH(Daily_Entry!A2:A999)=2)*(Daily_Entry!F2:F999))
A7: Other Expenses | B7: =SUMPRODUCT((MONTH(Daily_Entry!A2:A999)=2)*(Daily_Entry!G2:G999))
A8: Driver Salary | B8: =SUMIF(Driver_Salary!A:A,"Feb",Driver_Salary!B:B)
A9: Total Expenses | B9: =B6+B7+B8
A10: Net Profit | B10: =B3-B9

Sheet Mar
A1: Metric | B1: Value
A2: Total Loads | B2: =SUMPRODUCT((MONTH(Daily_Entry!A2:A999)=3)*(Daily_Entry!B2:B999))
A3: Total Income | B3: =SUMPRODUCT((MONTH(Daily_Entry!A2:A999)=3)*(Daily_Entry!C2:C999))
A4: Total GPay | B4: =SUMPRODUCT((MONTH(Daily_Entry!A2:A999)=3)*(Daily_Entry!D2:D999))
A5: Total Cash | B5: =SUMPRODUCT((MONTH(Daily_Entry!A2:A999)=3)*(Daily_Entry!E2:E999))
A6: Diesel Expense | B6: =SUMPRODUCT((MONTH(Daily_Entry!A2:A999)=3)*(Daily_Entry!F2:F999))
A7: Other Expenses | B7: =SUMPRODUCT((MONTH(Daily_Entry!A2:A999)=3)*(Daily_Entry!G2:G999))
A8: Driver Salary | B8: =SUMIF(Driver_Salary!A:A,"Mar",Driver_Salary!B:B)
A9: Total Expenses | B9: =B6+B7+B8
A10: Net Profit | B10: =B3-B9

Sheet Apr
A1: Metric | B1: Value
A2: Total Loads | B2: =SUMPRODUCT((MONTH(Daily_Entry!A2:A999)=4)*(Daily_Entry!B2:B999))
A3: Total Income | B3: =SUMPRODUCT((MONTH(Daily_Entry!A2:A999)=4)*(Daily_Entry!C2:C999))
A4: Total GPay | B4: =SUMPRODUCT((MONTH(Daily_Entry!A2:A999)=4)*(Daily_Entry!D2:D999))
A5: Total Cash | B5: =SUMPRODUCT((MONTH(Daily_Entry!A2:A999)=4)*(Daily_Entry!E2:E999))
A6: Diesel Expense | B6: =SUMPRODUCT((MONTH(Daily_Entry!A2:A999)=4)*(Daily_Entry!F2:F999))
A7: Other Expenses | B7: =SUMPRODUCT((MONTH(Daily_Entry!A2:A999)=4)*(Daily_Entry!G2:G999))
A8: Driver Salary | B8: =SUMIF(Driver_Salary!A:A,"Apr",Driver_Salary!B:B)
A9: Total Expenses | B9: =B6+B7+B8
A10: Net Profit | B10: =B3-B9

Sheet May
A1: Metric | B1: Value
A2: Total Loads | B2: =SUMPRODUCT((MONTH(Daily_Entry!A2:A999)=5)*(Daily_Entry!B2:B999))
A3: Total Income | B3: =SUMPRODUCT((MONTH(Daily_Entry!A2:A999)=5)*(Daily_Entry!C2:C999))
A4: Total GPay | B4: =SUMPRODUCT((MONTH(Daily_Entry!A2:A999)=5)*(Daily_Entry!D2:D999))
A5: Total Cash | B5: =SUMPRODUCT((MONTH(Daily_Entry!A2:A999)=5)*(Daily_Entry!E2:E999))
A6: Diesel Expense | B6: =SUMPRODUCT((MONTH(Daily_Entry!A2:A999)=5)*(Daily_Entry!F2:F999))
A7: Other Expenses | B7: =SUMPRODUCT((MONTH(Daily_Entry!A2:A999)=5)*(Daily_Entry!G2:G999))
A8: Driver Salary | B8: =SUMIF(Driver_Salary!A:A,"May",Driver_Salary!B:B)
A9: Total Expenses | B9: =B6+B7+B8
A10: Net Profit | B10: =B3-B9

Sheet Jun
A1: Metric | B1: Value
A2: Total Loads | B2: =SUMPRODUCT((MONTH(Daily_Entry!A2:A999)=6)*(Daily_Entry!B2:B999))
A3: Total Income | B3: =SUMPRODUCT((MONTH(Daily_Entry!A2:A999)=6)*(Daily_Entry!C2:C999))
A4: Total GPay | B4: =SUMPRODUCT((MONTH(Daily_Entry!A2:A999)=6)*(Daily_Entry!D2:D999))
A5: Total Cash | B5: =SUMPRODUCT((MONTH(Daily_Entry!A2:A999)=6)*(Daily_Entry!E2:E999))
A6: Diesel Expense | B6: =SUMPRODUCT((MONTH(Daily_Entry!A2:A999)=6)*(Daily_Entry!F2:F999))
A7: Other Expenses | B7: =SUMPRODUCT((MONTH(Daily_Entry!A2:A999)=6)*(Daily_Entry!G2:G999))
A8: Driver Salary | B8: =SUMIF(Driver_Salary!A:A,"Jun",Driver_Salary!B:B)
A9: Total Expenses | B9: =B6+B7+B8
A10: Net Profit | B10: =B3-B9

Sheet Jul
A1: Metric | B1: Value
A2: Total Loads | B2: =SUMPRODUCT((MONTH(Daily_Entry!A2:A999)=7)*(Daily_Entry!B2:B999))
A3: Total Income | B3: =SUMPRODUCT((MONTH(Daily_Entry!A2:A999)=7)*(Daily_Entry!C2:C999))
A4: Total GPay | B4: =SUMPRODUCT((MONTH(Daily_Entry!A2:A999)=7)*(Daily_Entry!D2:D999))
A5: Total Cash | B5: =SUMPRODUCT((MONTH(Daily_Entry!A2:A999)=7)*(Daily_Entry!E2:E999))
A6: Diesel Expense | B6: =SUMPRODUCT((MONTH(Daily_Entry!A2:A999)=7)*(Daily_Entry!F2:F999))
A7: Other Expenses | B7: =SUMPRODUCT((MONTH(Daily_Entry!A2:A999)=7)*(Daily_Entry!G2:G999))
A8: Driver Salary | B8: =SUMIF(Driver_Salary!A:A,"Jul",Driver_Salary!B:B)
A9: Total Expenses | B9: =B6+B7+B8
A10: Net Profit | B10: =B3-B9

Sheet Aug
A1: Metric | B1: Value
A2: Total Loads | B2: =SUMPRODUCT((MONTH(Daily_Entry!A2:A999)=8)*(Daily_Entry!B2:B999))
A3: Total Income | B3: =SUMPRODUCT((MONTH(Daily_Entry!A2:A999)=8)*(Daily_Entry!C2:C999))
A4: Total GPay | B4: =SUMPRODUCT((MONTH(Daily_Entry!A2:A999)=8)*(Daily_Entry!D2:D999))
A5: Total Cash | B5: =SUMPRODUCT((MONTH(Daily_Entry!A2:A999)=8)*(Daily_Entry!E2:E999))
A6: Diesel Expense | B6: =SUMPRODUCT((MONTH(Daily_Entry!A2:A999)=8)*(Daily_Entry!F2:F999))
A7: Other Expenses | B7: =SUMPRODUCT((MONTH(Daily_Entry!A2:A999)=8)*(Daily_Entry!G2:G999))
A8: Driver Salary | B8: =SUMIF(Driver_Salary!A:A,"Aug",Driver_Salary!B:B)
A9: Total Expenses | B9: =B6+B7+B8
A10: Net Profit | B10: =B3-B9

Sheet Sep
A1: Metric | B1: Value
A2: Total Loads | B2: =SUMPRODUCT((MONTH(Daily_Entry!A2:A999)=9)*(Daily_Entry!B2:B999))
A3: Total Income | B3: =SUMPRODUCT((MONTH(Daily_Entry!A2:A999)=9)*(Daily_Entry!C2:C999))
A4: Total GPay | B4: =SUMPRODUCT((MONTH(Daily_Entry!A2:A999)=9)*(Daily_Entry!D2:D999))
A5: Total Cash | B5: =SUMPRODUCT((MONTH(Daily_Entry!A2:A999)=9)*(Daily_Entry!E2:E999))
A6: Diesel Expense | B6: =SUMPRODUCT((MONTH(Daily_Entry!A2:A999)=9)*(Daily_Entry!F2:F999))
A7: Other Expenses | B7: =SUMPRODUCT((MONTH(Daily_Entry!A2:A999)=9)*(Daily_Entry!G2:G999))
A8: Driver Salary | B8: =SUMIF(Driver_Salary!A:A,"Sep",Driver_Salary!B:B)
A9: Total Expenses | B9: =B6+B7+B8
A10: Net Profit | B10: =B3-B9

Sheet Oct
A1: Metric | B1: Value
A2: Total Loads | B2: =SUMPRODUCT((MONTH(Daily_Entry!A2:A999)=10)*(Daily_Entry!B2:B999))
A3: Total Income | B3: =SUMPRODUCT((MONTH(Daily_Entry!A2:A999)=10)*(Daily_Entry!C2:C999))
A4: Total GPay | B4: =SUMPRODUCT((MONTH(Daily_Entry!A2:A999)=10)*(Daily_Entry!D2:D999))
A5: Total Cash | B5: =SUMPRODUCT((MONTH(Daily_Entry!A2:A999)=10)*(Daily_Entry!E2:E999))
A6: Diesel Expense | B6: =SUMPRODUCT((MONTH(Daily_Entry!A2:A999)=10)*(Daily_Entry!F2:F999))
A7: Other Expenses | B7: =SUMPRODUCT((MONTH(Daily_Entry!A2:A999)=10)*(Daily_Entry!G2:G999))
A8: Driver Salary | B8: =SUMIF(Driver_Salary!A:A,"Oct",Driver_Salary!B:B)
A9: Total Expenses | B9: =B6+B7+B8
A10: Net Profit | B10: =B3-B9

Sheet Nov
A1: Metric | B1: Value
A2: Total Loads | B2: =SUMPRODUCT((MONTH(Daily_Entry!A2:A999)=11)*(Daily_Entry!B2:B999))
A3: Total Income | B3: =SUMPRODUCT((MONTH(Daily_Entry!A2:A999)=11)*(Daily_Entry!C2:C999))
A4: Total GPay | B4: =SUMPRODUCT((MONTH(Daily_Entry!A2:A999)=11)*(Daily_Entry!D2:D999))
A5: Total Cash | B5: =SUMPRODUCT((MONTH(Daily_Entry!A2:A999)=11)*(Daily_Entry!E2:E999))
A6: Diesel Expense | B6: =SUMPRODUCT((MONTH(Daily_Entry!A2:A999)=11)*(Daily_Entry!F2:F999))
A7: Other Expenses | B7: =SUMPRODUCT((MONTH(Daily_Entry!A2:A999)=11)*(Daily_Entry!G2:G999))
A8: Driver Salary | B8: =SUMIF(Driver_Salary!A:A,"Nov",Driver_Salary!B:B)
A9: Total Expenses | B9: =B6+B7+B8
A10: Net Profit | B10: =B3-B9

Sheet Dec
A1: Metric | B1: Value
A2: Total Loads | B2: =SUMPRODUCT((MONTH(Daily_Entry!A2:A999)=12)*(Daily_Entry!B2:B999))
A3: Total Income | B3: =SUMPRODUCT((MONTH(Daily_Entry!A2:A999)=12)*(Daily_Entry!C2:C999))
A4: Total GPay | B4: =SUMPRODUCT((MONTH(Daily_Entry!A2:A999)=12)*(Daily_Entry!D2:D999))
A5: Total Cash | B5: =SUMPRODUCT((MONTH(Daily_Entry!A2:A999)=12)*(Daily_Entry!E2:E999))
A6: Diesel Expense | B6: =SUMPRODUCT((MONTH(Daily_Entry!A2:A999)=12)*(Daily_Entry!F2:F999))
A7: Other Expenses | B7: =SUMPRODUCT((MONTH(Daily_Entry!A2:A999)=12)*(Daily_Entry!G2:G999))
A8: Driver Salary | B8: =SUMIF(Driver_Salary!A:A,"Dec",Driver_Salary!B:B)
A9: Total Expenses | B9: =B6+B7+B8
A10: Net Profit | B10: =B3-B9

Sheet Yearly_Summary
A1: Month | B1: Income | C1: Expenses | D1: Profit
A2: Jan | B2: ='Jan'!B3 | C2: ='Jan'!B9 | D2: ='Jan'!B10
A3: Feb | B3: ='Feb'!B3 | C3: ='Feb'!B9 | D3: ='Feb'!B10
A4: Mar | B4: ='Mar'!B3 | C4: ='Mar'!B9 | D4: ='Mar'!B10
A5: Apr | B5: ='Apr'!B3 | C5: ='Apr'!B9 | D5: ='Apr'!B10
A6: May | B6: ='May'!B3 | C6: ='May'!B9 | D6: ='May'!B10
A7: Jun | B7: ='Jun'!B3 | C7: ='Jun'!B9 | D7: ='Jun'!B10
A8: Jul | B8: ='Jul'!B3 | C8: ='Jul'!B9 | D8: ='Jul'!B10
A9: Aug | B9: ='Aug'!B3 | C9: ='Aug'!B9 | D9: ='Aug'!B10
A10: Sep | B10: ='Sep'!B3 | C10: ='Sep'!B9 | D10: ='Sep'!B10
A11: Oct | B11: ='Oct'!B3 | C11: ='Oct'!B9 | D11: ='Oct'!B10
A12: Nov | B12: ='Nov'!B3 | C12: ='Nov'!B9 | D12: ='Nov'!B10
A13: Dec | B13: ='Dec'!B3 | C13: ='Dec'!B9 | D13: ='Dec'!B10
